Workbook

Sheet Collectée
A1: Libre | B1: Compte | C1: Clé d'appel | E1: C | F1: Solde
B2: 70100000 | C2: VENTES | D2: RECETTES RESTAURANT 10% | E2: 249560.65 | F2: =-E2 -> -249560.65
B3: 70100001 | C3: RECETTE | D3: RECETTES RESTO.10% FREDDY | E3: 1229860.9 | F3: =-E3 -> -1229860.9
B4: 70101000 | C4: PRODUIT | D4: RECETTES RESTAURANT 20% | E4: 49856.22 | F4: =-E4 -> -49856.22
B5: 70110000 | C5: RECETTE | D5: RECETTES RESTAURANT 20% | E5: 256448.77 | F5: =-E5 -> -256448.77
B6: 70110001 | C6: RECETTE | D6: RECETTES RESTO.20% FREDDY | F6: =-E6 -> 0
B7: 70140000 | C7: VAE55 | D7: VAE 5,5% | E7: 21213.37 | F7: =-E7 -> -21213.37
F8: =SUM(F2:F7) -> -1806939.9
G10: TVA Calculée | H10: Ecart
B11: 44571100 | C11: TVACOLL | D11: TVA COLLECTEE 20% | E11: 44585.46 | F11: -51441.21
B12: 44571110 | D12: TVA COLLECTEE 5,50% | E12: 1029.35 | F12: -1045.22
B13: 44571160 | C13: TVACOLL | D13: TVA COLLECTEE 10% | E13: 109056.68 | F13: -126471.89

Sheet Feuil2
A1: CJ | B1: Folio | C1: Ligne | D1: Date | E1: Compte | F1: Libellé | G1: Débit | H1: Let. | I1: Crédit | J1: Taux
A2: VE | F2: VENTES (01.2023) | G2: 0 | I2: 0
A3: VE | B3: 0 | C3: 1 | D3: 44957 | E3: 70100001 | F3: CA FREDDY 2023=01 | G3: 0 | I3: 64482 | J3: 0.1
A4: VE | B4: 0 | C4: 2 | D4: 44957 | E4: 44571160 | F4: CA FREDDY 2023=01 | G4: 0 | I4: 6454 | J4: 0.1
A5: VE | B5: 0 | C5: 3 | D5: 44957 | E5: 70110001 | F5: CA FREDDY 2023=01 | G5: 0 | I5: 14671 | J5: 0.2
A6: VE | B6: 0 | C6: 4 | D6: 44957 | E6: 44571100 | F6: CA FREDDY 2023=01 | G6: 0 | I6: 2934 | J6: 0.2
A7: VE | B7: 0 | C7: 5 | D7: 44957 | E7: 70140000 | F7: CA FREDDY 2023=01 | G7: 0 | I7: 168
A8: VE | B8: 0 | C8: 6 | D8: 44957 | E8: 44571110 | F8: CA FREDDY 2023=01 | G8: 0 | I8: 9
A9: VE | B9: 0 | C9: 7 | D9: 44957 | E9: 79140000 | F9: CA FREDDY 2023=01 | G9: 0 | I9: 281
A10: VE | B10: 0 | C10: 8 | D10: 44957 | E10: 90000000 | F10: CA FREDDY 2023=01 | G10: 837 | I10: 0
A11: VE | B11: 0 | C11: 9 | D11: 44957 | E11: 51150000 | F11: CA FREDDY 2023=01 | G11: 70573 | I11: 0
A12: VE | B12: 0 | C12: 10 | D12: 44957 | E12: 51120000 | F12: CA FREDDY 2023=01 | G12: 62 | I12: 0
A13: VE | B13: 0 | C13: 11 | D13: 44957 | E13: 53000000 | F13: CA FREDDY 2023=01 | G13: 17251 | I13: 0
A14: VE | B14: 0 | C14: 12 | D14: 44957 | E14: 51180000 | F14: CA FREDDY 2023=01 | G14: 1196 | I14: 0
A15: VE | B15: 0 | C15: 13 | D15: 44957 | E15: 53000000 | F15: CA FREDDY 2023=01 | G15: 0 | I15: 920
G16: 0 | I16: 0
A17: VE | B17: 0 | C17: 14 | D17: 44957 | E17: 70100000 | F17: CA Bonbao 2023=01 | G17: 0 | I17: 11306 | J17: 0.1
A18: VE | B18: 0 | C18: 15 | D18: 44957 | E18: 44571160 | F18: CA Bonbao 2023=01 | G18: 0 | I18: 1132 | J18: 0.1
A19: VE | B19: 0 | C19: 16 | D19: 44957 | E19: 70101000 | F19: CA Bonbao 2023=01 | G19: 0 | I19: 679 | J19: 0.2
A20: VE | B20: 0 | C20: 17 | D20: 44957 | E20: 44571100 | F20: CA Bonbao 2023=01 | G20: 0 | I20: 136 | J20: 0.2
A21: VE | B21: 0 | C21: 18 | D21: 44957 | E21: 90000000 | F21: CA Bonbao 2023=01 | G21: 166 | I21: 0
A22: VE | B22: 0 | C22: 19 | D22: 44957 | E22: 90000000 | F22: CA Bonbao 2023=01 | G22: 131 | I22: 0
A23: VE | B23: 0 | C23: 20 | D23: 44957 | E23: 51150000 | F23: CA Bonbao 2023=01 | G23: 10352 | I23: 0
A24: VE | B24: 0 | C24: 21 | D24: 44957 | E24: 53000000 | F24: CA Bonbao 2023=01 | G24: 1957 | I24: 0
A25: VE | B25: 0 | C25: 22 | D25: 44957 | E25: 51180000 | F25: CA Bonbao 2023=01 | G25: 728 | I25: 0
A26: VE | B26: 0 | C26: 23 | D26: 44957 | E26: 53000000 | F26: CA Bonbao 2023=01 | G26: 0 | I26: 82
G27: 0 | I27: 0
A28: VE | F28: Clients | G28: 1134 | I28: 0
A29: VE | F29: Généraux | G29: 102119 | I29: 103253
A30: VE | F30: TOTAL VENTES (01.2023) | G30: 103253 | I30: 103253
A31: VE | F31: VENTES (02.2023) | G31: 0 | I31: 0
A32: VE | B32: 0 | C32: 1 | D32: 44985 | E32: 70100001 | F32: CA 202302 | G32: 0 | I32: 66603 | J32: 0.1
A33: VE | B33: 0 | C33: 2 | D33: 44985 | E33: 44571160 | F33: CA 202302 | G33: 0 | I33: 6667 | J33: 0.1
A34: VE | B34: 0 | C34: 3 | D34: 44985 | E34: 70110000 | F34: CA 202302 | G34: 0 | I34: 15863 | J34: 0.2
A35: VE | B35: 0 | C35: 4 | D35: 44985 | E35: 44571100 | F35: CA 202302 | G35: 0 | I35: 3172 | J35: 0.2
A36: VE | B36: 0 | C36: 5 | D36: 44985 | E36: 70140000 | F36: CA 202302 | G36: 0 | I36: 130
A37: VE | B37: 0 | C37: 6 | D37: 44985 | E37: 44571110 | F37: CA 202302 | G37: 0 | I37: 7
A38: VE | B38: 0 | C38: 7 | D38: 44985 | E38: 79100000 | F38: CA 202302 | G38: 0 | I38: 548
A39: VE | B39: 0 | C39: 8 | D39: 44985 | E39: 51150000 | F39: CA 202302 | G39: 74557 | I39: 0
A40: VE | B40: 0 | C40: 9 | D40: 44985 | E40: 90CLI | F40: CA 202302 | G40: 579 | I40: 0
A41: VE | B41: 0 | C41: 10 | D41: 44985 | E41: 53100000 | F41: CA 202302 | G41: 17588 | I41: 0
A42: VE | B42: 0 | C42: 11 | D42: 44985 | E42: 51170000 | F42: CA 202302 | G42: 900 | I42: 0
A43: VE | B43: 0 | C43: 12 | D43: 44985 | E43: 53100000 | F43: CA 202302 | G43: 0 | I43: 634
G44: 0 | I44: 0
A45: VE | B45: 0 | C45: 13 | D45: 44985 | E45: 70100000 | F45: CA 2023 02 BB | G45: 0 | I45: 7990 | J45: 0.1
A46: VE | B46: 0 | C46: 14 | D46: 44985 | E46: 44571160 | F46: CA 2023 02 BB | G46: 0 | I46: 799 | J46: 0.1
A47: VE | B47: 0 | C47: 15 | D47: 44985 | E47: 70101000 | F47: CA 2023 02 BB | G47: 0 | I47: 627 | J47: 0.2
A48: VE | B48: 0 | C48: 16 | D48: 44985 | E48: 44571100 | F48: CA 2023 02 BB | G48: 0 | I48: 125 | J48: 0.2
A49: VE | B49: 0 | C49: 17 | D49: 44985 | E49: 51150000 | F49: CA 2023 02 BB | G49: 8235 | I49: 0
A50: VE | B50: 0 | C50: 18 | D50: 44985 | E50: 53100000 | F50: CA 2023 02 BB | G50: 1039 | I50: 0
A51: VE | B51: 0 | C51: 19 | D51: 44985 | E51: 51170000 | F51: CA 2023 02 BB | G51: 327 | I51: 0
A52: VE | B52: 0 | C52: 20 | D52: 44985 | E52: 53100000 | F52: CA 2023 02 BB | G52: 0 | I52: 59
G53: 0 | I53: 0
A54: VE | F54: Clients | G54: 579 | I54: 0
A55: VE | F55: Généraux | G55: 102647 | I55: 103226
A56: VE | F56: TOTAL VENTES (02.2023) | G56: 103226 | I56: 103226
A57: VE | F57: VENTES (03.2023) | G57: 0 | I57: 0
A58: VE | B58: 0 | C58: 1 | D58: 45016 | E58: 79140000 | F58: CA2023 03 | G58: 0 | I58: 45
A59: VE | B59: 0 | C59: 2 | D59: 45016 | E59: 70100001 | F59: CA2023 03 | G59: 0 | I59: 64381 | J59: 0.1
A60: VE | B60: 0 | C60: 3 | D60: 45016 | E60: 44571160 | F60: CA2023 03 | G60: 0 | I60: 6444 | J60: 0.1
A61: VE | B61: 0 | C61: 4 | D61: 45016 | E61: 70110000 | F61: CA2023 03 | G61: 0 | I61: 16101 | J61: 0.2
A62: VE | B62: 0 | C62: 5 | D62: 45016 | E62: 44571100 | F62: CA2023 03 | G62: 0 | I62: 3220 | J62: 0.2
A63: VE | B63: 0 | C63: 6 | D63: 45016 | E63: 70140000 | F63: CA2023 03 | G63: 0 | I63: 86
A64: VE | B64: 0 | C64: 7 | D64: 45016 | E64: 44571110 | F64: CA2023 03 | G64: 0 | I64: 5
A65: VE | B65: 0 | C65: 8 | D65: 45016 | E65: 51150000 | F65: CA2023 03 | G65: 73823 | I65: 0
A66: VE | B66: 0 | C66: 9 | D66: 45016 | E66: 90CLI | F66: CA2023 03 | G66: 1187 | I66: 0
A67: VE | B67: 0 | C67: 10 | D67: 45016 | E67: 51120000 | F67: CA2023 03 | G67: 101 | I67: 0
A68: VE | B68: 0 | C68: 11 | D68: 45016 | E68: 53100000 | F68: CA2023 03 | G68: 15199 | I68: 0
A69: VE | B69: 0 | C69: 12 | D69: 45016 | E69: 51170000 | F69: CA2023 03 | G69: 834 | I69: 0
A70: VE | B70: 0 | C70: 13 | D70: 45016 | E70: 53100000 | F70: CA2023 03 | G70: 0 | I70: 862
G71: 0 | I71: 0
A72: VE | B72: 0 | C72: 14 | D72: 45016 | E72: 70100000 | F72: CA 202303 BB | G72: 0 | I72: 15114 | J72: 0.1
A73: VE | B73: 0 | C73: 15 | D73: 45016 | E73: 44571160 | F73: CA 202303 BB | G73: 0 | I73: 1512 | J73: 0.1
A74: VE | B74: 0 | C74: 16 | D74: 45016 | E74: 70101000 | F74: CA 202303 BB | G74: 0 | I74: 1284 | J74: 0.2
A75: VE | B75: 0 | C75: 17 | D75: 45016 | E75: 44571100 | F75: CA 202303 BB | G75: 0 | I75: 257 | J75: 0.2
A76: VE | B76: 0 | C76: 18 | D76: 45016 | E76: 90CLI | F76: CA 202303 BB | G76: 2 | I76: 0
A77: VE | B77: 0 | C77: 19 | D77: 45016 | E77: 90CLI | F77: CA 202303 BB AVOIR | G77: 36 | I77: 0
A78: VE | B78: 0 | C78: 20 | D78: 45016 | E78: 51150000 | F78: CA 202303 BB AVOIR | G78: 14917 | I78: 0
A79: VE | B79: 0 | C79: 21 | D79: 45016 | E79: 53100000 | F79: CA 202303 BB AVOIR | G79: 2128 | I79: 0
A80: VE | B80: 0 | C80: 22 | D80: 45016 | E80: 51170000 | F80: CA 202303 BB AVOIR | G80: 935 | I80: 0
A81: VE | B81: 0 | C81: 23 | D81: 45016 | E81: 90CLI | F81: CA 202303 BB AVOIR | G81: 290 | I81: 0
A82: VE | B82: 0 | C82: 24 | D82: 45016 | E82: 53100000 | F82: CA 202303 BB AVOIR | G82: 0 | I82: 142
G83: 0 | I83: 0
A84: VE | F84: Clients | G84: 1515 | I84: 0
A85: VE | F85: Généraux | G85: 107938 | I85: 109453
A86: VE | F86: TOTAL VENTES (03.2023) | G86: 109453 | I86: 109453
A87: VE | F87: VENTES (04.2023) | G87: 0 | I87: 0
A88: VE | B88: 0 | C88: 1 | D88: 45046 | E88: 79140000 | F88: CA 2023 04 | G88: 0 | I88: 75
A89: VE | B89: 0 | C89: 2 | D89: 45046 | E89: 70100001 | F89: CA 2023 04 | G89: 0 | I89: 90522 | J89: 0.1
A90: VE | B90: 0 | C90: 3 | D90: 45046 | E90: 44571160 | F90: CA 2023 04 | G90: 0 | I90: 9061 | J90: 0.1
A91: VE | B91: 0 | C91: 4 | D91: 45046 | E91: 70110000 | F91: CA 2023 04 | G91: 0 | I91: 20979 | J91: 0.2
A92: VE | B92: 0 | C92: 5 | D92: 45046 | E92: 44571100 | F92: CA 2023 04 | G92: 0 | I92: 4195 | J92: 0.2
A93: VE | B93: 0 | C93: 6 | D93: 45046 | E93: 70140000 | F93: CA 2023 04 | G93: 0 | I93: 228
A94: VE | B94: 0 | C94: 7 | D94: 45046 | E94: 44571110 | F94: CA 2023 04 | G94: 0 | I94: 13
A95: VE | B95: 0 | C95: 8 | D95: 45046 | E95: 90CLIENT | F95: CA 2023 04 | G95: 539 | I95: 0
A96: VE | B96: 0 | C96: 9 | D96: 45046 | E96: 51150000 | F96: CA 2023 04 | G96: 101292 | I96: 0
A97: VE | B97: 0 | C97: 10 | D97: 45046 | E97: 51120000 | F97: CA 2023 04 | G97: 1493 | I97: 0
A98: VE | B98: 0 | C98: 11 | D98: 45046 | E98: 53100000 | F98: CA 2023 04 | G98: 22493 | I98: 0
A99: VE | B99: 0 | C99: 12 | D99: 45046 | E99: 51170000 | F99: CA 2023 04 | G99: 641 | I99: 0
A100: VE | B100: 0 | C100: 13 | D100: 45046 | E100: 51120000 | F100: CA 2023 04 | G100: 108 | I100: 0
...

Sheet Declaration
A1: Période | B1: Ventes, prestations de services | C1: Taux normal 20 % | D1: Taux Réduit | E1: Total Base | F1: TVA Taux réduit 5,5% | G1: TVA Taux Réduit 10% | H1: TVA Taux Normal 20% | I1: Total TVA Brute | J1: Biens constituant des immobilisations | K1: TVA Déductible | L1: Report Crédit de TVA | M1: Crédit de TVA | N1: TVA Due
B2: A1 | C2: 08 | F2: 09 | G2: 9B | I2: 16 | J2: 19 | K2: 20 | L2: 22 | M2: 25 | N2: TD
A3: 2024-01 | B3: 73379.21 | C3: 15031 | D3: 6243.74 | E3: =SUM(B3:D3) -> 94653.95 | F3: =D3*0.055 -> 343.4057 | G3: =+B3*0.1 -> 7337.921 | H3: =C3*0.2 -> 3006.2 | I3: =SUM(F3:H3) -> 10687.527 | K3: =64425.56-2.76+4431.05 -> 68853.85 | M3: =K3-I3 -> 58166.323
A4: 2024-02 | B4: 84010.61 | C4: 17604.4 | D4: 7207.78 | E4: =SUM(B4:D4) -> 108822.79 | F4: =D4*0.055 -> 396.4279 | G4: =+B4*0.1 -> 8401.061 | H4: =C4*0.2 -> 3520.88 | I4: =SUM(F4:H4) -> 12318.369 | K4: =6332.22+9.56 -> 6341.78 | L4: =+M3 -> 58166.323 | M4: =+L4+K4-I4 -> 52189.734
A5: 2024-03 | B5: 110950 | C5: 23821.67 | D5: 3926.13 | E5: =SUM(B5:D5) -> 138697.8 | F5: =D5*0.055 -> 215.93715 | G5: =+B5*0.1 -> 11095 | H5: =C5*0.2 -> 4764.334 | I5: =SUM(F5:H5) -> 16075.271 | K5: 7615 | L5: =+M4 -> 52189.734 | M5: =+L5+K5-I5 -> 43729.463
A6: 2024-04 | B6: =105772+10960.34 -> 116732.34 | C6: =2616.84+21532.15 -> 24148.99 | D6: 2180.52 | E6: =SUM(B6:D6) -> 143061.85 | F6: =D6*0.055 -> 119.9286 | G6: =+B6*0.1 -> 11673.234 | H6: =C6*0.2 -> 4829.798 | I6: =SUM(F6:H6) -> 16622.961 | K6: =9351.55-125.81 -> 9225.74 | L6: =+M5 -> 43729.463 | M6: =+L6+K6-I6 -> 36332.243
A7: 2024-05 | B7: =114167.6+15504.87 -> 129672.47 | C7: =3970.12+24930.8 -> 28900.92 | D7: 1115.47 | E7: =SUM(B7:D7) -> 159688.86 | F7: =D7*0.055 -> 61.35085 | G7: =+B7*0.1 -> 12967.247 | H7: =C7*0.2 -> 5780.184 | I7: =SUM(F7:H7) -> 18808.782 | K7: =7376.46-144.07 -> 7232.39 | L7: =+M6 -> 36332.243 | M7: =+L7+K7-I7 -> 24755.851
A8: 2024-06 | B8: =13592.67+78226.22 -> 91818.89 | C8: =3124.13+17263.74 -> 20387.87 | D8: 539.73 | E8: =SUM(B8:D8) -> 112746.49 | F8: =D8*0.055 -> 29.68515 | G8: =+B8*0.1 -> 9181.889 | H8: =C8*0.2 -> 4077.574 | I8: =SUM(F8:H8) -> 13289.148 | K8: =6940.65-10.38 -> 6930.27 | L8: =+M7 -> 24755.851 | M8: =+L8+K8-I8 -> 18396.973
A9: 2024-07 | B9: =18831.77+89343.68 -> 108175.45 | C9: =3920.2+18717.67 -> 22637.87 | E9: =SUM(B9:D9) -> 130813.32 | F9: =D9*0.055 -> 0 | G9: =+B9*0.1 -> 10817.545 | H9: =C9*0.2 -> 4527.574 | I9: =SUM(F9:H9) -> 15345.119 | K9: =8288.83-61.24 -> 8227.59 | L9: =+M8 -> 18396.973 | M9: =+L9+K9-I9 -> 11279.444
A10: 2024-08 | B10: =31922.35+114553.06 -> 146475.41 | C10: =5937.64+23484.1 -> 29421.74 | E10: =SUM(B10:D10) -> 175897.15 | F10: =D10*0.055 -> 0 | G10: =+B10*0.1 -> 14647.541 | H10: =C10*0.2 -> 5884.348 | I10: =SUM(F10:H10) -> 20531.889 | K10: 7830.52 | L10: =+M9 -> 11279.444 | N10: 1422
A11: 2024-09 | B11: =32074.24+92215.31 -> 124289.55 | C11: =6492.98+21462.94 -> 27955.92 | E11: =SUM(B11:D11) -> 152245.47 | F11: =D11*0.055 -> 0 | G11: =+B11*0.1 -> 12428.955 | H11: =C11*0.2 -> 5591.184 | I11: =SUM(F11:H11) -> 18020.139 | K11: 8705.92 | N11: =+I11-K11 -> 9314.219
A12: 2024-10 | B12: =33459.28+99104.19 -> 132563.47 | C12: =6470.88+21396.94 -> 27867.82 | E12: =SUM(B12:D12) -> 160431.29 | F12: =D12*0.055 -> 0 | G12: =+B12*0.1 -> 13256.347 | H12: =C12*0.2 -> 5573.564 | I12: =SUM(F12:H12) -> 18829.911 | K12: =10164.63-7.43 -> 10157.2 | N12: =+I12-K12 -> 8672.711
A13: 2024-11 | B13: =35668.64+98064.78 -> 133733.42 | C13: =6730.64+20993.62 -> 27724.26 | E13: =SUM(B13:D13) -> 161457.68 | F13: =D13*0.055 -> 0 | G13: =+B13*0.1 -> 13373.342 | H13: =C13*0.2 -> 5544.852 | I13: =SUM(F13:H13) -> 18918.194 | K13: 7724.72 | N13: =+I13-K13-J13 -> 11193.474
A14: 2024-12 | B14: =57546.49+170072.98 -> 227619.47 | C14: =10592.79+30209.74 -> 40802.53 | E14: =SUM(B14:D14) -> 268422 | F14: =D14*0.055 -> 0 | G14: =+B14*0.1 -> 22761.947 | H14: =C14*0.2 -> 8160.506 | I14: =SUM(F14:H14) -> 30922.453 | K14: 10199.47 | N14: =+I14-K14-J14-L14 -> 20722.983
B15: =SUM(B3:B14) -> 1479420.3 | C15: =SUM(C3:C14) -> 306304.99 | D15: =SUM(D3:D14) -> 21213.37 | E15: =SUM(B15:D15) -> 1806938.7 | F15: =SUM(F3:F14) -> 1166.7353 | G15: =SUM(G3:G14) -> 147942.03 | H15: =SUM(H3:H14) -> 61260.998 | I15: =SUM(I3:I14) -> 210369.76 | J15: =SUM(J3:J14) -> 0 | K15: 13965.26 | L15: =SUM(L3:L11) -> 244850.03 | M15: =SUM(M3:M10) -> 244850.03 | N15: =+I15-K15-J15 -> 196404.5
A16: Bases à déclarer | B16: =+Collectée!E2+Collectée!E3 -> 1479421.5 | C16: =Collectée!E4+Collectée!E5 -> 306304.99 | D16: =Collectée!E7 -> 21213.37 | F16: =-Collectée!F7 -> 21213.37 | G16: =+-Collectée!F2-Collectée!F3 -> 1479421.5 | I16: =+C16*0.2+F16*0.055+G16*0.1 -> 210369.89 | J16: =+'TVA Ded'!G4 -> 5331.65 | K16: 13965.26
A17: Ecart à déclarer | B17: =+B16-B15 -> 1.25 | C17: =+C16-C15 -> 0 | D17: =+D16-D15 -> 0 | F17: =+F16-F15 -> 20046.635 | G17: =+G16-G15 -> 1331479.5 | I17: =SUM(C17:G17) -> 1351526.1 | J17: =+J16-J15 -> 5331.65 | K17: 13965.26 | N17: =+I17-K17 -> 1337560.9
I18: =+Collectée!F11+Collectée!F12+Collectée!F13 -> -178958.32
F19: =+F14*0.055 -> 0
G20: =+G14+C14 -> 63564.477

Sheet TVA Ded
B4: 44562000 | C4: TVADED | D4: TVA DEDUCT.S/IMMO. 20 % | E4: 5331.65 | G4: 5331.65
B5: 44566000 | C5: TVADED | D5: TVA DEDUCT.S/ACHATS & F.G | E5: 84838.79 | F5: 178.5 | G5: 84660.29
B6: 44566100 | C6: TVADEDU | D6: TVA DEDUCTIBLE 20% | E6: 590.63 | F6: 2.81 | G6: 587.82
B7: 44566110 | C7: TVADEDU | D7: TVA DEDUCTIBLE 5.5% | E7: 168.71 | G7: 168.71
B8: 44566120 | D8: TVA déductible 2,10% Débits | E8: 0.1 | G8: 0.1
B9: 44566160 | C9: TVADEDU | D9: TVA DEDUCTIBLE 10% | E9: 147.06 | F9: 25.72 | G9: 121.34
G10: =SUM(G4:G9) -> 90869.91
B13: 44562000 | C13: TVADED | D13: TVA DEDUCT.S/IMMO. 20 % | E13: 5331.65 | G13: 5331.65
B14: 44566000 | C14: TVADED | D14: TVA DEDUCT.S/ACHATS & F.G | E14: 84838.79 | F14: 178.5 | G14: 84660.29
B15: 44566100 | C15: TVADEDU | D15: TVA DEDUCTIBLE 20% | E15: 590.63 | F15: 2.81 | G15: 587.82
B16: 44566110 | C16: TVADEDU | D16: TVA DEDUCTIBLE 5.5% | E16: 168.71 | G16: 168.71
B17: 44566120 | D17: TVA déductible 2,10% Débits | E17: 0.1 | G17: 0.1
B18: 44566160 | C18: TVADEDU | D18: TVA DEDUCTIBLE 10% | E18: 147.06 | F18: 25.72 | G18: 121.34
